pencil_art/__init__.py
pencil_art/core.py
pencil_art-0.1.8.dist-info/LICENSE
pencil_art-0.1.8.dist-info/METADATA
pencil_art-0.1.8.dist-info/WHEEL
pencil_art-0.1.8.dist-info/top_level.txt
pencil_art-0.1.8.dist-info/RECORD
