Metadata-Version: 2.1
Name: pencil_art
Version: 0.1.8
Summary: Pencil Art Generator from Images
Home-page: https://github.com/webbro-software/pencil-art
Author: Usmonov Shoxruxmirzo
Author-email: usmonovshohruxmirzo@gmail.com
Classifier: Programming Language :: Python :: 3
Classifier: License :: OSI Approved :: MIT License
Classifier: Operating System :: OS Independent
Requires-Python: >=3.6
License-File: LICENSE
Requires-Dist: opencv-python
